drain_swamp_snippet/__init__.py
drain_swamp_snippet/__init__.pyi
drain_swamp_snippet/check_type.py
drain_swamp_snippet/check_type.pyi
drain_swamp_snippet/constants.py
drain_swamp_snippet/constants.pyi
drain_swamp_snippet/py.typed
drain_swamp_snippet/snip.py
drain_swamp_snippet/snip.pyi
drain_swamp_snippet-1.0.2.dist-info/LICENSE
drain_swamp_snippet-1.0.2.dist-info/METADATA
drain_swamp_snippet-1.0.2.dist-info/NOTICE.txt
drain_swamp_snippet-1.0.2.dist-info/WHEEL
drain_swamp_snippet-1.0.2.dist-info/top_level.txt
drain_swamp_snippet-1.0.2.dist-info/RECORD
