Metadata-Version: 2.1
Name: drain-swamp-snippet
Version: 1.0.2
Summary: Change portions of static config files
Author-email: Dave Faulkmore <faulkmore@protonmail.com>
License:                     GNU AFFERO GENERAL PUBLIC LICENSE
Project-URL: Changes, https://raw.githubusercontent.com/msftcangoblowm/drain-swamp-snippet/master/CHANGES.rst
Project-URL: Source code, https://github.com/msftcangoblowm/drain-swamp-snippet
Project-URL: Issue tracker, https://github.com/msftcangoblowm/drain-swamp-snippet/issues
Project-URL: Mastodon, https://mastodon.social/@msftcangoblowme
Keywords: snippet,pyproject.toml,Sphinx conf.py
Classifier: Environment :: Console
Classifier: Development Status :: 4 - Beta
Classifier: Intended Audience :: Developers
Classifier: License :: OSI Approved :: GNU Affero General Public License v3 or later (AGPLv3+)
Classifier: Operating System :: OS Independent
Classifier: Programming Language :: Python :: 3
Classifier: Programming Language :: Python :: 3.9
Classifier: Programming Language :: Python :: 3.10
Classifier: Programming Language :: Python :: 3.11
Classifier: Programming Language :: Python :: 3.12
Classifier: Programming Language :: Python :: 3.13
Classifier: Programming Language :: Python :: Implementation :: CPython
Classifier: Programming Language :: Python :: Implementation :: PyPy
Classifier: Topic :: Text Processing
Classifier: Typing :: Typed
Requires-Python: >=3.9
License-File: LICENSE
License-File: NOTICE.txt
Provides-Extra: dev
Requires-Dist: appdirs==1.4.4; extra == "dev"
Requires-Dist: attrs==24.3.0; extra == "dev"
Requires-Dist: backports-tarfile==1.2.0; extra == "dev"
Requires-Dist: black==24.8.0; extra == "dev"
Requires-Dist: blackdoc==0.3.9; extra == "dev"
Requires-Dist: certifi==2024.8.30; extra == "dev"
Requires-Dist: cffi==1.17.1; extra == "dev"
Requires-Dist: charset-normalizer==3.3.2; extra == "dev"
Requires-Dist: click==8.1.7; extra == "dev"
Requires-Dist: coverage[toml]==7.6.1; extra == "dev"
Requires-Dist: cryptography==43.0.1; extra == "dev"
Requires-Dist: docutils==0.21.2; extra == "dev"
Requires-Dist: exceptiongroup==1.2.2; extra == "dev"
Requires-Dist: fastjsonschema==2.20.0; extra == "dev"
Requires-Dist: flake8==7.1.1; extra == "dev"
Requires-Dist: flake8-pyi==24.6.0; extra == "dev"
Requires-Dist: flake8-pyproject==1.2.3; extra == "dev"
Requires-Dist: idna==3.10; extra == "dev"
Requires-Dist: importlib-metadata==8.5.0; extra == "dev"
Requires-Dist: iniconfig==2.0.0; extra == "dev"
Requires-Dist: isort==5.13.2; extra == "dev"
Requires-Dist: jaraco-classes==3.4.0; extra == "dev"
Requires-Dist: jaraco-context==6.0.1; extra == "dev"
Requires-Dist: jaraco-functools==4.0.2; extra == "dev"
Requires-Dist: jeepney==0.8.0; extra == "dev"
Requires-Dist: keyring==25.3.0; extra == "dev"
Requires-Dist: logging-strict==1.4.2; extra == "dev"
Requires-Dist: markdown-it-py==3.0.0; extra == "dev"
Requires-Dist: mccabe==0.7.0; extra == "dev"
Requires-Dist: mdurl==0.1.2; extra == "dev"
Requires-Dist: more-itertools==10.5.0; extra == "dev"
Requires-Dist: mypy==1.11.2; extra == "dev"
Requires-Dist: mypy-extensions==1.0.0; extra == "dev"
Requires-Dist: nh3==0.2.18; extra == "dev"
Requires-Dist: packaging==24.1; extra == "dev"
Requires-Dist: pathspec==0.12.1; extra == "dev"
Requires-Dist: pkginfo==1.10.0; extra == "dev"
Requires-Dist: platformdirs==4.3.3; extra == "dev"
Requires-Dist: pluggy==1.5.0; extra == "dev"
Requires-Dist: pycodestyle==2.12.1; extra == "dev"
Requires-Dist: pycparser==2.22; extra == "dev"
Requires-Dist: pyflakes==3.2.0; extra == "dev"
Requires-Dist: pygments==2.18.0; extra == "dev"
Requires-Dist: pytest==8.3.3; extra == "dev"
Requires-Dist: pytest-datadir==1.5.0; extra == "dev"
Requires-Dist: pytest-logging-strict==0.1.0.post1; extra == "dev"
Requires-Dist: pytest-regressions==2.5.0; extra == "dev"
Requires-Dist: python-dateutil==2.9.0.post0; extra == "dev"
Requires-Dist: pyyaml==6.0.2; extra == "dev"
Requires-Dist: readme-renderer==44.0; extra == "dev"
Requires-Dist: requests==2.32.3; extra == "dev"
Requires-Dist: requests-toolbelt==1.0.0; extra == "dev"
Requires-Dist: rfc3986==2.0.0; extra == "dev"
Requires-Dist: rich==13.8.1; extra == "dev"
Requires-Dist: secretstorage==3.3.3; extra == "dev"
Requires-Dist: six==1.17.0; extra == "dev"
Requires-Dist: strictyaml==1.7.3; extra == "dev"
Requires-Dist: tomli==2.0.2; python_version < "3.11" and extra == "dev"
Requires-Dist: twine==5.1.1; extra == "dev"
Requires-Dist: types-setuptools==74.1.0.20240907; extra == "dev"
Requires-Dist: typing-extensions==4.12.2; extra == "dev"
Requires-Dist: urllib3==2.2.3; extra == "dev"
Requires-Dist: validate-pyproject==0.19; extra == "dev"
Requires-Dist: zipp==3.20.2; extra == "dev"
